KeyMaze_300_downloader-1.0.6.data/scripts/km-downloader
etc/udev/rules.d/90-KeyMaze300.rules
km/__init__.py
km/downloadkeymaze300.py
km/gpx.py
km/km-plug-dialog.py
km/kml.py
usr/share/km/firsttrackpoints.bin
usr/share/km/nexttrackpoints.bin
usr/share/km/waypoints.bin
KeyMaze_300_downloader-1.0.6.dist-info/AUTHORS
KeyMaze_300_downloader-1.0.6.dist-info/LICENSE
KeyMaze_300_downloader-1.0.6.dist-info/METADATA
KeyMaze_300_downloader-1.0.6.dist-info/WHEEL
KeyMaze_300_downloader-1.0.6.dist-info/top_level.txt
KeyMaze_300_downloader-1.0.6.dist-info/RECORD
