Metadata-Version: 2.1
Name: KeyMaze-300-downloader
Version: 1.0.6
Summary: Keymaze 300
Home-page: https://pypi.org/project/KeyMaze-300-downloader/:q
Author: Vincent-Xavier JUMEL
Author-email: endymion@thetys-retz.net
License: GPL-3
Platform: UNKNOWN
Requires: serial
